setup.py
libhttp/__init__.py
libhttp/libhttp.py
libhttp.egg-info/PKG-INFO
libhttp.egg-info/SOURCES.txt
libhttp.egg-info/dependency_links.txt
libhttp.egg-info/top_level.txt