Metadata-Version: 1.1
Name: libhttp
Version: 0.4.0
Summary: A library for handling http urls
Home-page: https://github.com/antonybholmes/libhttp
Author: Antony B Holmes
Author-email: antony.b.holmes@gmail.com
License: UNKNOWN
Platform: UNKNOWN
Classifier: Programming Language :: Python :: 3
Classifier: License :: OSI Approved :: MIT License
Classifier: Operating System :: OS Independent
